pytest_test_analyzer/__init__.py
pytest_test_analyzer/analyzer.py
pytest_test_analyzer/cli.py
pytest_test_analyzer/static/analyzing.png
pytest_test_analyzer/templates/report_template.html
pytest_test_analyzer-0.1.1.dist-info/METADATA
pytest_test_analyzer-0.1.1.dist-info/WHEEL
pytest_test_analyzer-0.1.1.dist-info/entry_points.txt
pytest_test_analyzer-0.1.1.dist-info/top_level.txt
pytest_test_analyzer-0.1.1.dist-info/RECORD
