Metadata-Version: 2.4
Name: pytest-test-analyzer
Version: 0.1.1
Summary: A powerful tool for analyzing pytest test files and generating detailed reports
Home-page: https://github.com/deekshith-poojary98/pytest-test-analyzer
Author: Deekshith Poojary
Author-email: Deekshith Poojary <deekshithpoojary355@gmail.com>
Maintainer: Deekshith Poojary
Maintainer-email: Deekshith Poojary <deekshithpoojary355@gmail.com>
License: MIT
Project-URL: Homepage, https://github.com/deekshith-poojary98/pytest-test-analyzer
Project-URL: Repository, https://github.com/deekshith-poojary98/pytest-test-analyzer.git
Keywords: pytest,testing,test-analysis,test-automation,test-reports,test-statistics
Classifier: Programming Language :: Python :: 3
Classifier: Programming Language :: Python :: 3.7
Classifier: Programming Language :: Python :: 3.8
Classifier: Programming Language :: Python :: 3.9
Classifier: Programming Language :: Python :: 3.10
Classifier: Programming Language :: Python :: 3.11
Classifier: License :: OSI Approved :: MIT License
Classifier: Operating System :: OS Independent
Classifier: Framework :: Pytest
Classifier: Intended Audience :: Developers
Classifier: Topic :: Software Development :: Testing
Classifier: Topic :: Software Development :: Libraries :: Python Modules
Classifier: Development Status :: 4 - Beta
Requires-Python: >=3.7
Requires-Dist: jinja2>=3.1.2
Dynamic: author
Dynamic: home-page
Dynamic: maintainer
Dynamic: requires-python
